{
    "id": "4efe3004-fd76-4149-8d0e-87b954e18811",
    "status": "completed",
    "text": "Eres todo lo que pedía, lo que me amaba, hacía, quería sentir Eres lo que tanto esperaba, lo que en sueños buscaba y que en ti descubrí Tú has llegado a encender cada parte de mi alma cada espacio de mi ser Ya no tengo corazón ni ojos para nadie, solo para ti. Eres el amor de mi vida, el destino lo sabía y hoy te puso ante mí Y cada vez que miro al pasado es que entiendo que a tu lado siempre pertenecí Tú has llegado a encender cada parte de mi alma, cada espacio de mi ser Ya no tengo corazón ni ojos para nadie. Solo para ti, Solo para ti, Solo para ti, Solo para ti. Es un po a ti. Eres todo lo que pedía, lo que no conocía y que en ti descubrí.",
    "words": [
        {
            "text": "Eres",
            "start": 3040,
            "end": 3400,
            "confidence": 0.7807617,
            "speaker": "A"
        },
        {
            "text": "todo",
            "start": 3400,
            "end": 3760,
            "confidence": 0.92285156,
            "speaker": "A"
        },
        {
            "text": "lo",
            "start": 3920,
            "end": 4320,
            "confidence": 0.73095703,
            "speaker": "A"
        },
        {
            "text": "que",
            "start": 5120,
            "end": 5520,
            "confidence": 0.8520508,
            "speaker": "A"
        },
        {
            "text": "pedía,",
            "start": 5600,
            "end": 6880,
            "confidence": 0.9352214,
            "speaker": "A"
        },
        {
            "text": "lo",
            "start": 7280,
            "end": 7520,
            "confidence": 1.0,
            "speaker": "A"
        },
        {
            "text": "que",
            "start": 7520,
            "end": 7680,
            "confidence": 1.0,
            "speaker": "A"
        },
        {
            "text": "me",
            "start": 7680,
            "end": 8000,
            "confidence": 0.96240234,
            "speaker": "A"
        },
        {
            "text": "amaba,",
            "start": 8000,
            "end": 9200,
            "confidence": 0.7741699,
            "speaker": "A"
        },
        {
            "text": "hacía,",
            "start": 9440,
            "end": 10000,
            "confidence": 0.5192871,
            "speaker": "A"
        },
        {
            "text": "quería",
            "start": 10800,
            "end": 12000,
            "confidence": 0.9659831,
            "speaker": "A"
        },
        {
            "text": "sentir",
            "start": 12160,
            "end": 13120,
            "confidence": 1.0,
            "speaker": "A"
        },
        {
            "text": "Eres",
            "start": 16079,
            "end": 16640,
            "confidence": 0.7805176,
            "speaker": "A"
        },
        {
            "text": "lo",
            "start": 16640,
            "end": 16800,
            "confidence": 1.0,
            "speaker": "A"
        },
        {
            "text": "que",
            "start": 16800,
            "end": 17040,
            "confidence": 0.9819336,
            "speaker": "A"
        },
        {
            "text": "tanto",
            "start": 17120,
            "end": 18440,
            "confidence": 1.0,
            "speaker": "A"
        },
        {
            "text": "esperaba,",
            "start": 18440,
            "end": 19440,
            "confidence": 0.90201825,
            "speaker": "A"
        },
        {
            "text": "lo",
            "start": 20400,
            "end": 20640,
            "confidence": 0.99072266,
            "speaker": "A"
        },
        {
            "text": "que",
            "start": 20640,
            "end": 20800,
            "confidence": 1.0,
            "speaker": "A"
        },
        {
            "text": "en",
            "start": 20800,
            "end": 21000,
            "confidence": 0.9819336,
            "speaker": "A"
        },
        {
            "text": "sueños",
            "start": 21000,
            "end": 21720,
            "confidence": 0.96691895,
            "speaker": "A"
        },
        {
            "text": "buscaba",
            "start": 21720,
            "end": 22640,
            "confidence": 0.68619794,
            "speaker": "A"
        },
        {
            "text": "y",
            "start": 23520,
            "end": 23800,
            "confidence": 1.0,
            "speaker": "A"
        },
        {
            "text": "que",
            "start": 23800,
            "end": 24040,
            "confidence": 0.77734375,
            "speaker": "A"
        },
        {
            "text": "en",
            "start": 24040,
            "end": 24280,
            "confidence": 1.0,
            "speaker": "A"
        },
        {
            "text": "ti",
            "start": 24280,
            "end": 24880,
            "confidence": 0.9995117,
            "speaker": "A"
        },
        {
            "text": "descubrí",
            "start": 25040,
            "end": 26160,
            "confidence": 0.9926758,
            "speaker": "A"
        },
        {
            "text": "Tú",
            "start": 29280,
            "end": 29600,
            "confidence": 0.8859863,
            "speaker": "A"
        },
        {
            "text": "has",
            "start": 30320,
            "end": 30600,
            "confidence": 0.9975586,
            "speaker": "A"
        },
        {
            "text": "llegado",
            "start": 30600,
            "end": 31040,
            "confidence": 0.90844727,
            "speaker": "A"
        },
        {
            "text": "a",
            "start": 31120,
            "end": 31440,
            "confidence": 0.8847656,
            "speaker": "A"
        },
        {
            "text": "encender",
            "start": 31440,
            "end": 31920,
            "confidence": 0.80444336,
            "speaker": "A"
        },
        {
            "text": "cada",
            "start": 33520,
            "end": 33920,
            "confidence": 0.9995117,
            "speaker": "A"
        },
        {
            "text": "parte",
            "start": 33920,
            "end": 34320,
            "confidence": 1.0,
            "speaker": "A"
        },
        {
            "text": "de",
            "start": 34400,
            "end": 34800,
            "confidence": 0.99609375,
            "speaker": "A"
        },
        {
            "text": "mi",
            "start": 34800,
            "end": 35200,
            "confidence": 0.9941406,
            "speaker": "A"
        },
        {
            "text": "alma",
            "start": 35360,
            "end": 35920,
            "confidence": 0.8642578,
            "speaker": "A"
        },
        {
            "text": "cada",
            "start": 36800,
            "end": 37160,
            "confidence": 0.99902344,
            "speaker": "A"
        },
        {
            "text": "espacio",
            "start": 37160,
            "end": 37880,
            "confidence": 0.91015625,
            "speaker": "A"
        },
        {
            "text": "de",
            "start": 37880,
            "end": 38120,
            "confidence": 0.99902344,
            "speaker": "A"
        },
        {
            "text": "mi",
            "start": 38120,
            "end": 38480,
            "confidence": 0.9848633,
            "speaker": "A"
        },
        {
            "text": "ser",
            "start": 38560,
            "end": 38960,
            "confidence": 0.9980469,
            "speaker": "A"
        },
        {
            "text": "Ya",
            "start": 40000,
            "end": 40280,
            "confidence": 0.99853516,
            "speaker": "A"
        },
        {
            "text": "no",
            "start": 40280,
            "end": 40480,
            "confidence": 1.0,
            "speaker": "A"
        },
        {
            "text": "tengo",
            "start": 40480,
            "end": 41040,
            "confidence": 0.99975586,
            "speaker": "A"
        },
        {
            "text": "corazón",
            "start": 41040,
            "end": 42320,
            "confidence": 0.90966797,
            "speaker": "A"
        },
        {
            "text": "ni",
            "start": 43360,
            "end": 43680,
            "confidence": 0.9975586,
            "speaker": "A"
        },
        {
            "text": "ojos",
            "start": 43680,
            "end": 44280,
            "confidence": 0.8414714,
            "speaker": "A"
        },
        {
            "text": "para",
            "start": 44280,
            "end": 44640,
            "confidence": 0.9995117,
            "speaker": "A"
        },
        {
            "text": "nadie,",
            "start": 44720,
            "end": 45920,
            "confidence": 0.88378906,
            "speaker": "A"
        },
        {
            "text": "solo",
            "start": 47840,
            "end": 48240,
            "confidence": 0.8803711,
            "speaker": "A"
        },
        {
            "text": "para",
            "start": 48320,
            "end": 48720,
            "confidence": 0.9995117,
            "speaker": "A"
        },
        {
            "text": "ti.",
            "start": 48880,
            "end": 49520,
            "confidence": 0.8083496,
            "speaker": "A"
        },
        {
            "text": "Eres",
            "start": 55290,
            "end": 55770,
            "confidence": 0.9980469,
            "speaker": "A"
        },
        {
            "text": "el",
            "start": 55770,
            "end": 55970,
            "confidence": 1.0,
            "speaker": "A"
        },
        {
            "text": "amor",
            "start": 55970,
            "end": 56330,
            "confidence": 0.99975586,
            "speaker": "A"
        },
        {
            "text": "de",
            "start": 57370,
            "end": 57650,
            "confidence": 1.0,
            "speaker": "A"
        },
        {
            "text": "mi",
            "start": 57650,
            "end": 57810,
            "confidence": 1.0,
            "speaker": "A"
        },
        {
            "text": "vida,",
            "start": 57810,
            "end": 58090,
            "confidence": 1.0,
            "speaker": "A"
        },
        {
            "text": "el",
            "start": 59290,
            "end": 59530,
            "confidence": 1.0,
            "speaker": "A"
        },
        {
            "text": "destino",
            "start": 59530,
            "end": 59930,
            "confidence": 0.9506836,
            "speaker": "A"
        },
        {
            "text": "lo",
            "start": 60090,
            "end": 60450,
            "confidence": 0.54345703,
            "speaker": "A"
        },
        {
            "text": "sabía",
            "start": 60450,
            "end": 61610,
            "confidence": 0.98535156,
            "speaker": "A"
        },
        {
            "text": "y",
            "start": 62410,
            "end": 62690,
            "confidence": 0.99853516,
            "speaker": "A"
        },
        {
            "text": "hoy",
            "start": 62690,
            "end": 62930,
            "confidence": 1.0,
            "speaker": "A"
        },
        {
            "text": "te",
            "start": 62930,
            "end": 63090,
            "confidence": 1.0,
            "speaker": "A"
        },
        {
            "text": "puso",
            "start": 63090,
            "end": 63610,
            "confidence": 0.83219403,
            "speaker": "A"
        },
        {
            "text": "ante",
            "start": 63610,
            "end": 64130,
            "confidence": 0.9367676,
            "speaker": "A"
        },
        {
            "text": "mí",
            "start": 64130,
            "end": 64650,
            "confidence": 0.80566406,
            "speaker": "A"
        },
        {
            "text": "Y",
            "start": 67610,
            "end": 67970,
            "confidence": 0.8173828,
            "speaker": "A"
        },
        {
            "text": "cada",
            "start": 67970,
            "end": 68290,
            "confidence": 1.0,
            "speaker": "A"
        },
        {
            "text": "vez",
            "start": 68290,
            "end": 68530,
            "confidence": 1.0,
            "speaker": "A"
        },
        {
            "text": "que",
            "start": 68530,
            "end": 68810,
            "confidence": 1.0,
            "speaker": "A"
        },
        {
            "text": "miro",
            "start": 68810,
            "end": 70050,
            "confidence": 0.78222656,
            "speaker": "A"
        },
        {
            "text": "al",
            "start": 70050,
            "end": 70290,
            "confidence": 0.73095703,
            "speaker": "A"
        },
        {
            "text": "pasado",
            "start": 70290,
            "end": 71130,
            "confidence": 1.0,
            "speaker": "A"
        },
        {
            "text": "es",
            "start": 72170,
            "end": 72410,
            "confidence": 0.9995117,
            "speaker": "A"
        },
        {
            "text": "que",
            "start": 72410,
            "end": 72530,
            "confidence": 1.0,
            "speaker": "A"
        },
        {
            "text": "entiendo",
            "start": 72530,
            "end": 72970,
            "confidence": 1.0,
            "speaker": "A"
        },
        {
            "text": "que",
            "start": 72970,
            "end": 73250,
            "confidence": 1.0,
            "speaker": "A"
        },
        {
            "text": "a",
            "start": 73250,
            "end": 73450,
            "confidence": 1.0,
            "speaker": "A"
        },
        {
            "text": "tu",
            "start": 73450,
            "end": 73650,
            "confidence": 0.9770508,
            "speaker": "A"
        },
        {
            "text": "lado",
            "start": 73650,
            "end": 74410,
            "confidence": 0.9992676,
            "speaker": "A"
        },
        {
            "text": "siempre",
            "start": 75370,
            "end": 75770,
            "confidence": 1.0,
            "speaker": "A"
        },
        {
            "text": "pertenecí",
            "start": 75930,
            "end": 77610,
            "confidence": 0.83935547,
            "speaker": "A"
        },
        {
            "text": "Tú",
            "start": 80650,
            "end": 81130,
            "confidence": 0.9616699,
            "speaker": "A"
        },
        {
            "text": "has",
            "start": 81770,
            "end": 82090,
            "confidence": 1.0,
            "speaker": "A"
        },
        {
            "text": "llegado",
            "start": 82090,
            "end": 82610,
            "confidence": 0.9621582,
            "speaker": "A"
        },
        {
            "text": "a",
            "start": 82610,
            "end": 82890,
            "confidence": 0.98876953,
            "speaker": "A"
        },
        {
            "text": "encender",
            "start": 82890,
            "end": 83450,
            "confidence": 0.9394531,
            "speaker": "A"
        },
        {
            "text": "cada",
            "start": 84810,
            "end": 85210,
            "confidence": 0.9819336,
            "speaker": "A"
        },
        {
            "text": "parte",
            "start": 85590,
            "end": 85790,
            "confidence": 0.9980469,
            "speaker": "A"
        },
        {
            "text": "de",
            "start": 85790,
            "end": 86030,
            "confidence": 1.0,
            "speaker": "A"
        },
        {
            "text": "mi",
            "start": 86030,
            "end": 86310,
            "confidence": 0.62158203,
            "speaker": "A"
        },
        {
            "text": "alma,",
            "start": 86550,
            "end": 87030,
            "confidence": 0.9404297,
            "speaker": "A"
        },
        {
            "text": "cada",
            "start": 88070,
            "end": 88430,
            "confidence": 0.99609375,
            "speaker": "A"
        },
        {
            "text": "espacio",
            "start": 88430,
            "end": 88990,
            "confidence": 0.85335284,
            "speaker": "A"
        },
        {
            "text": "de",
            "start": 88990,
            "end": 89230,
            "confidence": 1.0,
            "speaker": "A"
        },
        {
            "text": "mi",
            "start": 89230,
            "end": 89510,
            "confidence": 0.8149414,
            "speaker": "A"
        },
        {
            "text": "ser",
            "start": 89670,
            "end": 90070,
            "confidence": 0.73095703,
            "speaker": "A"
        },
        {
            "text": "Ya",
            "start": 91190,
            "end": 91470,
            "confidence": 1.0,
            "speaker": "A"
        },
        {
            "text": "no",
            "start": 91470,
            "end": 91590,
            "confidence": 1.0,
            "speaker": "A"
        },
        {
            "text": "tengo",
            "start": 91590,
            "end": 92070,
            "confidence": 1.0,
            "speaker": "A"
        },
        {
            "text": "corazón",
            "start": 92150,
            "end": 93030,
            "confidence": 0.8494466,
            "speaker": "A"
        },
        {
            "text": "ni",
            "start": 94470,
            "end": 94790,
            "confidence": 0.9995117,
            "speaker": "A"
        },
        {
            "text": "ojos",
            "start": 94790,
            "end": 95390,
            "confidence": 0.9842122,
            "speaker": "A"
        },
        {
            "text": "para",
            "start": 95390,
            "end": 95670,
            "confidence": 0.6513672,
            "speaker": "A"
        },
        {
            "text": "nadie.",
            "start": 95910,
            "end": 96630,
            "confidence": 0.8541667,
            "speaker": "A"
        },
        {
            "text": "Solo",
            "start": 98710,
            "end": 99070,
            "confidence": 0.99902344,
            "speaker": "B"
        },
        {
            "text": "para",
            "start": 99070,
            "end": 99430,
            "confidence": 0.9243164,
            "speaker": "B"
        },
        {
            "text": "ti,",
            "start": 99750,
            "end": 100310,
            "confidence": 0.8598633,
            "speaker": "B"
        },
        {
            "text": "Solo",
            "start": 104870,
            "end": 105230,
            "confidence": 0.9980469,
            "speaker": "B"
        },
        {
            "text": "para",
            "start": 105230,
            "end": 105590,
            "confidence": 0.9042969,
            "speaker": "B"
        },
        {
            "text": "ti,",
            "start": 105830,
            "end": 106390,
            "confidence": 0.80566406,
            "speaker": "B"
        },
        {
            "text": "Solo",
            "start": 110950,
            "end": 111310,
            "confidence": 0.9946289,
            "speaker": "B"
        },
        {
            "text": "para",
            "start": 111310,
            "end": 111670,
            "confidence": 0.9399414,
            "speaker": "B"
        },
        {
            "text": "ti,",
            "start": 111990,
            "end": 112470,
            "confidence": 0.861084,
            "speaker": "B"
        },
        {
            "text": "Solo",
            "start": 116790,
            "end": 117180,
            "confidence": 0.84521484,
            "speaker": "B"
        },
        {
            "text": "para",
            "start": 117490,
            "end": 117730,
            "confidence": 0.7685547,
            "speaker": "B"
        },
        {
            "text": "ti.",
            "start": 117970,
            "end": 118450,
            "confidence": 0.80126953,
            "speaker": "B"
        },
        {
            "text": "Es",
            "start": 155070,
            "end": 155230,
            "confidence": 0.69677734,
            "speaker": "B"
        },
        {
            "text": "un",
            "start": 155230,
            "end": 155550,
            "confidence": 0.5830078,
            "speaker": "B"
        },
        {
            "text": "po",
            "start": 155550,
            "end": 155950,
            "confidence": 0.36645508,
            "speaker": "B"
        },
        {
            "text": "a",
            "start": 155950,
            "end": 156230,
            "confidence": 0.38867188,
            "speaker": "B"
        },
        {
            "text": "ti.",
            "start": 156230,
            "end": 156670,
            "confidence": 0.673584,
            "speaker": "B"
        },
        {
            "text": "Eres",
            "start": 167710,
            "end": 168270,
            "confidence": 0.7619629,
            "speaker": "A"
        },
        {
            "text": "todo",
            "start": 168350,
            "end": 168750,
            "confidence": 1.0,
            "speaker": "A"
        },
        {
            "text": "lo",
            "start": 168750,
            "end": 169150,
            "confidence": 1.0,
            "speaker": "A"
        },
        {
            "text": "que",
            "start": 169950,
            "end": 170270,
            "confidence": 0.9628906,
            "speaker": "A"
        },
        {
            "text": "pedía,",
            "start": 170270,
            "end": 171470,
            "confidence": 0.7867839,
            "speaker": "A"
        },
        {
            "text": "lo",
            "start": 172270,
            "end": 172510,
            "confidence": 1.0,
            "speaker": "A"
        },
        {
            "text": "que",
            "start": 172510,
            "end": 172670,
            "confidence": 0.99658203,
            "speaker": "A"
        },
        {
            "text": "no",
            "start": 172670,
            "end": 172990,
            "confidence": 0.79833984,
            "speaker": "A"
        },
        {
            "text": "conocía",
            "start": 173230,
            "end": 174750,
            "confidence": 0.78100586,
            "speaker": "A"
        },
        {
            "text": "y",
            "start": 175630,
            "end": 175950,
            "confidence": 1.0,
            "speaker": "A"
        },
        {
            "text": "que",
            "start": 175950,
            "end": 176150,
            "confidence": 0.6069336,
            "speaker": "A"
        },
        {
            "text": "en",
            "start": 176150,
            "end": 176350,
            "confidence": 0.72998047,
            "speaker": "A"
        },
        {
            "text": "ti",
            "start": 176350,
            "end": 176750,
            "confidence": 0.78100586,
            "speaker": "A"
        },
        {
            "text": "descubrí.",
            "start": 176830,
            "end": 178110,
            "confidence": 0.8314209,
            "speaker": "A"
        }
    ],
    "utterances": [
        {
            "text": "Eres todo lo que pedía, lo que me amaba, hacía, quería sentir Eres lo que tanto esperaba, lo que en sueños buscaba y que en ti descubrí Tú has llegado a encender cada parte de mi alma cada espacio de mi ser Ya no tengo corazón ni ojos para nadie, solo para ti. Eres el amor de mi vida, el destino lo sabía y hoy te puso ante mí Y cada vez que miro al pasado es que entiendo que a tu lado siempre pertenecí Tú has llegado a encender cada parte de mi alma, cada espacio de mi ser Ya no tengo corazón ni ojos para nadie.",
            "start": 3040,
            "end": 96630,
            "confidence": 0.92937595,
            "speaker": "A"
        },
        {
            "text": "Solo para ti, Solo para ti, Solo para ti, Solo para ti. Es un po a ti.",
            "start": 98710,
            "end": 156670,
            "confidence": 0.7888471,
            "speaker": "B"
        },
        {
            "text": "Eres todo lo que pedía, lo que no conocía y que en ti descubrí.",
            "start": 167710,
            "end": 178110,
            "confidence": 0.859779,
            "speaker": "A"
        }
    ],
    "chapters": [],
    "sentiment_analysis_results": [],
    "audio_duration": 189,
    "language_code": "es"
}